{
  "indexes": [
    {
      "collectionGroup": "suppliers",
      "queryScope": "COLLECTION",
      "fields": [
        {
          "fieldPath": "isActive",
          "order": "ASCENDING"
        },
        {
          "fieldPath": "name",
          "order": "ASCENDING"
        }
      ]
    },
    {
      "collectionGroup": "pricelist_items",
      "queryScope": "COLLECTION",
      "fields": [
        {
          "fieldPath": "supplierId",
          "order": "ASCENDING"
        },
        {
          "fieldPath": "matchStatus",
          "order": "ASCENDING"
        },
        {
          "fieldPath": "isNewProduct",
          "order": "ASCENDING"
        }
      ]
    },
    {
      "collectionGroup": "price_changes",
      "queryScope": "COLLECTION",
      "fields": [
        {
          "fieldPath": "changeDate",
          "order": "DESCENDING"
        },
        {
          "fieldPath": "isSignificant",
          "order": "ASCENDING"
        }
      ]
    },
    {
      "collectionGroup": "inventory_transactions",
      "queryScope": "COLLECTION",
      "fields": [
        {
          "fieldPath": "sku",
          "order": "ASCENDING"
        },
        {
          "fieldPath": "timestamp",
          "order": "DESCENDING"
        }
      ]
    },
    {
      "collectionGroup": "pos_transactions",
      "queryScope": "COLLECTION",
      "fields": [
        {
          "fieldPath": "timestamp",
          "order": "DESCENDING"
        },
        {
          "fieldPath": "status",
          "order": "ASCENDING"
        }
      ]
    },
    {
      "collectionGroup": "products",
      "queryScope": "COLLECTION",
      "fields": [
        {
          "fieldPath": "category",
          "order": "ASCENDING"
        },
        {
          "fieldPath": "isActive",
          "order": "ASCENDING"
        }
      ]
    },
    {
      "collectionGroup": "inventory_transactions",
      "queryScope": "COLLECTION",
      "fields": [
        {
          "fieldPath": "locationId",
          "order": "ASCENDING"
        },
        {
          "fieldPath": "timestamp",
          "order": "DESCENDING"
        }
      ]
    },
    {
      "collectionGroup": "price_changes",
      "queryScope": "COLLECTION",
      "fields": [
        {
          "fieldPath": "sku",
          "order": "ASCENDING"
        },
        {
          "fieldPath": "changeDate",
          "order": "DESCENDING"
        }
      ]
    },
    {
      "collectionGroup": "pos_transactions",
      "queryScope": "COLLECTION",
      "fields": [
        {
          "fieldPath": "userId",
          "order": "ASCENDING"
        },
        {
          "fieldPath": "timestamp",
          "order": "DESCENDING"
        }
      ]
    },
    {
      "collectionGroup": "products",
      "queryScope": "COLLECTION",
      "fields": [
        {
          "fieldPath": "isActive",
          "order": "ASCENDING"
        },
        {
          "fieldPath": "sku",
          "order": "ASCENDING"
        }
      ]
    }
  ],
  "fieldOverrides": []
}
